{
  "generated_at": "2026-07-24T07:34:03.123802+09:00",
  "summary": {
    "days": 16,
    "picks": 80,
    "avg_return_pct": -0.28,
    "win_rate_pct": 37.5
  },
  "entries": [
    {
      "date": "2026-07-24",
      "picks": [
        {
          "code": "950170",
          "name": "JTC",
          "market": "KOSDAQ",
          "base_price": 5010.0,
          "score": 93.0,
          "current_price": 5010.0,
          "return_pct": 0.0
        },
        {
          "code": "006360",
          "name": "GS건설",
          "market": "KOSPI",
          "base_price": 34400.0,
          "score": 90.0,
          "current_price": 34400.0,
          "return_pct": 0.0
        },
        {
          "code": "012630",
          "name": "HDC",
          "market": "KOSPI",
          "base_price": 23100.0,
          "score": 90.0,
          "current_price": 23100.0,
          "return_pct": 0.0
        },
        {
          "code": "079160",
          "name": "CJ CGV",
          "market": "KOSPI",
          "base_price": 4710.0,
          "score": 85.0,
          "current_price": 4710.0,
          "return_pct": 0.0
        },
        {
          "code": "047810",
          "name": "한국항공우주",
          "market": "KOSPI",
          "base_price": 164100.0,
          "score": 85.0,
          "current_price": 164100.0,
          "return_pct": 0.0
        }
      ],
      "avg_return_pct": 0.0
    },
    {
      "date": "2026-07-23",
      "picks": [
        {
          "code": "064820",
          "name": "케이프",
          "market": "KOSDAQ",
          "base_price": 9260.0,
          "score": 100.0,
          "current_price": 9290.0,
          "return_pct": 0.32
        },
        {
          "code": "049070",
          "name": "인탑스",
          "market": "KOSDAQ",
          "base_price": 18860.0,
          "score": 100.0,
          "current_price": 18740.0,
          "return_pct": -0.64
        },
        {
          "code": "017670",
          "name": "SK텔레콤",
          "market": "KOSPI",
          "base_price": 94100.0,
          "score": 93.0,
          "current_price": 99500.0,
          "return_pct": 5.74
        },
        {
          "code": "267250",
          "name": "HD현대",
          "market": "KOSPI",
          "base_price": 212000.0,
          "score": 85.0,
          "current_price": 231500.0,
          "return_pct": 9.2
        },
        {
          "code": "000270",
          "name": "기아",
          "market": "KOSPI",
          "base_price": 146800.0,
          "score": 85.0,
          "current_price": 149800.0,
          "return_pct": 2.04
        }
      ],
      "avg_return_pct": 3.33
    },
    {
      "date": "2026-07-22",
      "picks": [
        {
          "code": "192440",
          "name": "슈피겐코리아",
          "market": "KOSDAQ",
          "base_price": 30000.0,
          "score": 93.0,
          "current_price": 30600.0,
          "return_pct": 2.0
        },
        {
          "code": "005710",
          "name": "대원산업",
          "market": "KOSDAQ",
          "base_price": 10790.0,
          "score": 93.0,
          "current_price": 10820.0,
          "return_pct": 0.28
        },
        {
          "code": "099440",
          "name": "스맥",
          "market": "KOSDAQ",
          "base_price": 2990.0,
          "score": 90.0,
          "current_price": 3315.0,
          "return_pct": 10.87
        },
        {
          "code": "460930",
          "name": "현대힘스",
          "market": "KOSDAQ",
          "base_price": 12750.0,
          "score": 90.0,
          "current_price": 13020.0,
          "return_pct": 2.12
        },
        {
          "code": "214320",
          "name": "이노션",
          "market": "KOSPI",
          "base_price": 18610.0,
          "score": 85.0,
          "current_price": 19100.0,
          "return_pct": 2.63
        }
      ],
      "avg_return_pct": 3.58
    },
    {
      "date": "2026-07-21",
      "picks": [
        {
          "code": "298020",
          "name": "효성티앤씨",
          "market": "KOSPI",
          "base_price": 298000.0,
          "score": 100.0,
          "current_price": 322000.0,
          "return_pct": 8.05
        },
        {
          "code": "030190",
          "name": "NICE평가정보",
          "market": "KOSPI",
          "base_price": 14080.0,
          "score": 85.0,
          "current_price": 14530.0,
          "return_pct": 3.2
        },
        {
          "code": "279570",
          "name": "케이뱅크",
          "market": "KOSPI",
          "base_price": 6200.0,
          "score": 85.0,
          "current_price": 6220.0,
          "return_pct": 0.32
        },
        {
          "code": "036530",
          "name": "SNT홀딩스",
          "market": "KOSPI",
          "base_price": 52900.0,
          "score": 80.0,
          "current_price": 49850.0,
          "return_pct": -5.77
        },
        {
          "code": "441270",
          "name": "파인엠텍",
          "market": "KOSDAQ",
          "base_price": 6580.0,
          "score": 76.0,
          "current_price": 6860.0,
          "return_pct": 4.26
        }
      ],
      "avg_return_pct": 2.01
    },
    {
      "date": "2026-07-20",
      "picks": [
        {
          "code": "036530",
          "name": "SNT홀딩스",
          "market": "KOSPI",
          "base_price": 52000.0,
          "score": 93.0,
          "current_price": 49850.0,
          "return_pct": -4.13
        },
        {
          "code": "011780",
          "name": "금호석유화학",
          "market": "KOSPI",
          "base_price": 123500.0,
          "score": 85.0,
          "current_price": 125100.0,
          "return_pct": 1.3
        },
        {
          "code": "000810",
          "name": "삼성화재",
          "market": "KOSPI",
          "base_price": 701000.0,
          "score": 85.0,
          "current_price": 638000.0,
          "return_pct": -8.99
        },
        {
          "code": "000370",
          "name": "한화손해보험",
          "market": "KOSPI",
          "base_price": 6090.0,
          "score": 85.0,
          "current_price": 5770.0,
          "return_pct": -5.25
        },
        {
          "code": "033780",
          "name": "KT&G",
          "market": "KOSPI",
          "base_price": 179900.0,
          "score": 85.0,
          "current_price": 179600.0,
          "return_pct": -0.17
        }
      ],
      "avg_return_pct": -3.45
    },
    {
      "date": "2026-07-17",
      "picks": [
        {
          "code": "036530",
          "name": "SNT홀딩스",
          "market": "KOSPI",
          "base_price": 52000.0,
          "score": 93.0,
          "current_price": 49850.0,
          "return_pct": -4.13
        },
        {
          "code": "011780",
          "name": "금호석유화학",
          "market": "KOSPI",
          "base_price": 123500.0,
          "score": 85.0,
          "current_price": 125100.0,
          "return_pct": 1.3
        },
        {
          "code": "000810",
          "name": "삼성화재",
          "market": "KOSPI",
          "base_price": 701000.0,
          "score": 85.0,
          "current_price": 638000.0,
          "return_pct": -8.99
        },
        {
          "code": "000370",
          "name": "한화손해보험",
          "market": "KOSPI",
          "base_price": 6090.0,
          "score": 85.0,
          "current_price": 5770.0,
          "return_pct": -5.25
        },
        {
          "code": "033780",
          "name": "KT&G",
          "market": "KOSPI",
          "base_price": 179900.0,
          "score": 85.0,
          "current_price": 179600.0,
          "return_pct": -0.17
        }
      ],
      "avg_return_pct": -3.45
    },
    {
      "date": "2026-07-16",
      "picks": [
        {
          "code": "484120",
          "name": "도우인시스",
          "market": "KOSDAQ",
          "base_price": 18090.0,
          "score": 90.0,
          "current_price": 16860.0,
          "return_pct": -6.8
        },
        {
          "code": "267270",
          "name": "HD건설기계",
          "market": "KOSPI",
          "base_price": 129500.0,
          "score": 85.0,
          "current_price": 140300.0,
          "return_pct": 8.34
        },
        {
          "code": "004490",
          "name": "세방전지",
          "market": "KOSPI",
          "base_price": 55000.0,
          "score": 85.0,
          "current_price": 53800.0,
          "return_pct": -2.18
        },
        {
          "code": "021240",
          "name": "코웨이",
          "market": "KOSPI",
          "base_price": 95700.0,
          "score": 85.0,
          "current_price": 90700.0,
          "return_pct": -5.22
        },
        {
          "code": "353810",
          "name": "이지바이오",
          "market": "KOSDAQ",
          "base_price": 6380.0,
          "score": 85.0,
          "current_price": 6190.0,
          "return_pct": -2.98
        }
      ],
      "avg_return_pct": -1.77
    },
    {
      "date": "2026-07-15",
      "picks": [
        {
          "code": "045100",
          "name": "한양이엔지",
          "market": "KOSDAQ",
          "base_price": 32750.0,
          "score": 85.0,
          "current_price": 31550.0,
          "return_pct": -3.66
        },
        {
          "code": "035810",
          "name": "이지홀딩스",
          "market": "KOSDAQ",
          "base_price": 4425.0,
          "score": 85.0,
          "current_price": 4420.0,
          "return_pct": -0.11
        },
        {
          "code": "131290",
          "name": "티에스이",
          "market": "KOSDAQ",
          "base_price": 277000.0,
          "score": 83.0,
          "current_price": 239500.0,
          "return_pct": -13.54
        },
        {
          "code": "446540",
          "name": "메가터치",
          "market": "KOSDAQ",
          "base_price": 6570.0,
          "score": 75.0,
          "current_price": 6850.0,
          "return_pct": 4.26
        },
        {
          "code": "006120",
          "name": "SK디스커버리",
          "market": "KOSPI",
          "base_price": 54200.0,
          "score": 73.0,
          "current_price": 53800.0,
          "return_pct": -0.74
        }
      ],
      "avg_return_pct": -2.76
    },
    {
      "date": "2026-07-14",
      "picks": [
        {
          "code": "078130",
          "name": "국일제지",
          "market": "KOSDAQ",
          "base_price": 4005.0,
          "score": 85.0,
          "current_price": 4120.0,
          "return_pct": 2.87
        },
        {
          "code": "005300",
          "name": "롯데칠성",
          "market": "KOSPI",
          "base_price": 101600.0,
          "score": 85.0,
          "current_price": 99900.0,
          "return_pct": -1.67
        },
        {
          "code": "096770",
          "name": "SK이노베이션",
          "market": "KOSPI",
          "base_price": 110200.0,
          "score": 80.0,
          "current_price": 132200.0,
          "return_pct": 19.96
        },
        {
          "code": "219130",
          "name": "타이거일렉",
          "market": "KOSDAQ",
          "base_price": 72500.0,
          "score": 75.0,
          "current_price": 73500.0,
          "return_pct": 1.38
        },
        {
          "code": "491000",
          "name": "리브스메드",
          "market": "KOSDAQ",
          "base_price": 40350.0,
          "score": 75.0,
          "current_price": 38400.0,
          "return_pct": -4.83
        }
      ],
      "avg_return_pct": 3.54
    },
    {
      "date": "2026-07-13",
      "picks": [
        {
          "code": "200710",
          "name": "에이디테크놀로지",
          "market": "KOSDAQ",
          "base_price": 35450.0,
          "score": 90.0,
          "current_price": 27750.0,
          "return_pct": -21.72
        },
        {
          "code": "018290",
          "name": "브이티",
          "market": "KOSDAQ",
          "base_price": 12230.0,
          "score": 85.0,
          "current_price": 11660.0,
          "return_pct": -4.66
        },
        {
          "code": "096770",
          "name": "SK이노베이션",
          "market": "KOSPI",
          "base_price": 102900.0,
          "score": 85.0,
          "current_price": 132200.0,
          "return_pct": 28.47
        },
        {
          "code": "001450",
          "name": "현대해상",
          "market": "KOSPI",
          "base_price": 38150.0,
          "score": 85.0,
          "current_price": 38600.0,
          "return_pct": 1.18
        },
        {
          "code": "032640",
          "name": "LG유플러스",
          "market": "KOSPI",
          "base_price": 14960.0,
          "score": 85.0,
          "current_price": 14790.0,
          "return_pct": -1.14
        }
      ],
      "avg_return_pct": 0.43
    },
    {
      "date": "2026-07-10",
      "picks": [
        {
          "code": "071200",
          "name": "인피니트헬스케어",
          "market": "KOSDAQ",
          "base_price": 7910.0,
          "score": 90.0,
          "current_price": 8350.0,
          "return_pct": 5.56
        },
        {
          "code": "030000",
          "name": "제일기획",
          "market": "KOSPI",
          "base_price": 19990.0,
          "score": 85.0,
          "current_price": 18790.0,
          "return_pct": -6.0
        },
        {
          "code": "000080",
          "name": "하이트진로",
          "market": "KOSPI",
          "base_price": 15400.0,
          "score": 75.0,
          "current_price": 14980.0,
          "return_pct": -2.73
        },
        {
          "code": "181710",
          "name": "NHN",
          "market": "KOSPI",
          "base_price": 37900.0,
          "score": 75.0,
          "current_price": 38500.0,
          "return_pct": 1.58
        },
        {
          "code": "101730",
          "name": "위메이드맥스",
          "market": "KOSDAQ",
          "base_price": 4945.0,
          "score": 73.0,
          "current_price": 3790.0,
          "return_pct": -23.36
        }
      ],
      "avg_return_pct": -4.99
    },
    {
      "date": "2026-07-09",
      "picks": [
        {
          "code": "180400",
          "name": "DXVX",
          "market": "KOSDAQ",
          "base_price": 2440.0,
          "score": 93.0,
          "current_price": 2300.0,
          "return_pct": -5.74
        },
        {
          "code": "028670",
          "name": "팬오션",
          "market": "KOSPI",
          "base_price": 5170.0,
          "score": 85.0,
          "current_price": 5300.0,
          "return_pct": 2.51
        },
        {
          "code": "033780",
          "name": "KT&G",
          "market": "KOSPI",
          "base_price": 184300.0,
          "score": 85.0,
          "current_price": 179600.0,
          "return_pct": -2.55
        },
        {
          "code": "084110",
          "name": "휴온스글로벌",
          "market": "KOSDAQ",
          "base_price": 26600.0,
          "score": 85.0,
          "current_price": 25850.0,
          "return_pct": -2.82
        },
        {
          "code": "439090",
          "name": "마녀공장",
          "market": "KOSDAQ",
          "base_price": 17600.0,
          "score": 80.0,
          "current_price": 16340.0,
          "return_pct": -7.16
        }
      ],
      "avg_return_pct": -3.15
    },
    {
      "date": "2026-07-08",
      "picks": [
        {
          "code": "300720",
          "name": "한일시멘트",
          "market": "KOSPI",
          "base_price": 14690.0,
          "score": 93.0,
          "current_price": 14140.0,
          "return_pct": -3.74
        },
        {
          "code": "237880",
          "name": "클리오",
          "market": "KOSDAQ",
          "base_price": 11230.0,
          "score": 90.0,
          "current_price": 10200.0,
          "return_pct": -9.17
        },
        {
          "code": "079940",
          "name": "가비아",
          "market": "KOSDAQ",
          "base_price": 31850.0,
          "score": 85.0,
          "current_price": 47550.0,
          "return_pct": 49.29
        },
        {
          "code": "175330",
          "name": "JB금융지주",
          "market": "KOSPI",
          "base_price": 28000.0,
          "score": 85.0,
          "current_price": 25550.0,
          "return_pct": -8.75
        },
        {
          "code": "030200",
          "name": "KT",
          "market": "KOSPI",
          "base_price": 55500.0,
          "score": 85.0,
          "current_price": 52700.0,
          "return_pct": -5.05
        }
      ],
      "avg_return_pct": 4.52
    },
    {
      "date": "2026-07-07",
      "picks": [
        {
          "code": "036530",
          "name": "SNT홀딩스",
          "market": "KOSPI",
          "base_price": 52900.0,
          "score": 85.0,
          "current_price": 49850.0,
          "return_pct": -5.77
        },
        {
          "code": "139130",
          "name": "iM금융지주",
          "market": "KOSPI",
          "base_price": 18300.0,
          "score": 85.0,
          "current_price": 17940.0,
          "return_pct": -1.97
        },
        {
          "code": "151860",
          "name": "KG에코솔루션",
          "market": "KOSDAQ",
          "base_price": 5740.0,
          "score": 85.0,
          "current_price": 5500.0,
          "return_pct": -4.18
        },
        {
          "code": "018670",
          "name": "SK가스",
          "market": "KOSPI",
          "base_price": 227500.0,
          "score": 83.0,
          "current_price": 259500.0,
          "return_pct": 14.07
        },
        {
          "code": "052330",
          "name": "코텍",
          "market": "KOSDAQ",
          "base_price": 11380.0,
          "score": 75.0,
          "current_price": 12070.0,
          "return_pct": 6.06
        }
      ],
      "avg_return_pct": 1.64
    },
    {
      "date": "2026-07-06",
      "picks": [
        {
          "code": "069620",
          "name": "대웅제약",
          "market": "KOSPI",
          "base_price": 132500.0,
          "score": 90.0,
          "current_price": 123800.0,
          "return_pct": -6.57
        },
        {
          "code": "039830",
          "name": "오로라",
          "market": "KOSDAQ",
          "base_price": 20400.0,
          "score": 90.0,
          "current_price": 19130.0,
          "return_pct": -6.23
        },
        {
          "code": "026960",
          "name": "동서",
          "market": "KOSPI",
          "base_price": 25950.0,
          "score": 85.0,
          "current_price": 25850.0,
          "return_pct": -0.39
        },
        {
          "code": "105560",
          "name": "KB금융",
          "market": "KOSPI",
          "base_price": 170100.0,
          "score": 85.0,
          "current_price": 176300.0,
          "return_pct": 3.64
        },
        {
          "code": "034950",
          "name": "한국기업평가",
          "market": "KOSDAQ",
          "base_price": 101700.0,
          "score": 85.0,
          "current_price": 101400.0,
          "return_pct": -0.29
        }
      ],
      "avg_return_pct": -1.97
    },
    {
      "date": "2026-07-03",
      "picks": [
        {
          "code": "069620",
          "name": "대웅제약",
          "market": "KOSPI",
          "base_price": 132500.0,
          "score": 90.0,
          "current_price": 123800.0,
          "return_pct": -6.57
        },
        {
          "code": "039830",
          "name": "오로라",
          "market": "KOSDAQ",
          "base_price": 20400.0,
          "score": 90.0,
          "current_price": 19130.0,
          "return_pct": -6.23
        },
        {
          "code": "026960",
          "name": "동서",
          "market": "KOSPI",
          "base_price": 25950.0,
          "score": 85.0,
          "current_price": 25850.0,
          "return_pct": -0.39
        },
        {
          "code": "105560",
          "name": "KB금융",
          "market": "KOSPI",
          "base_price": 170100.0,
          "score": 85.0,
          "current_price": 176300.0,
          "return_pct": 3.64
        },
        {
          "code": "034950",
          "name": "한국기업평가",
          "market": "KOSDAQ",
          "base_price": 101700.0,
          "score": 85.0,
          "current_price": 101400.0,
          "return_pct": -0.29
        }
      ],
      "avg_return_pct": -1.97
    }
  ]
}